pyfix/__init__.py
pyfix/client_connection.py
pyfix/codec.py
pyfix/connection.py
pyfix/engine.py
pyfix/event.py
pyfix/journaler.py
pyfix/message.py
pyfix/server_connection.py
pyfix/session.py
pyfix/transaction.py
pyfix/FIX44/__init__.py
pyfix/FIX44/fixtags.py
pyfix/FIX44/messages.py
pyfix/FIX44/msgtype.py
pyfix_fork-0.1.dist-info/LICENSE
pyfix_fork-0.1.dist-info/METADATA
pyfix_fork-0.1.dist-info/WHEEL
pyfix_fork-0.1.dist-info/top_level.txt
pyfix_fork-0.1.dist-info/RECORD
