Metadata-Version: 2.1
Name: pyfix-fork
Version: 0.1
Summary: pyfix
Home-page: https://github.com/wannabegeek/PyFIX/
Author: Tom Fewster
Author-email: tom@wanabegeek.com
Maintainer: Eddy Pronk
Maintainer-email: epronk@muftor.com
License: UNKNOWN
Download-URL: https://github.com/wannabegeek/PyFIX/
Platform: UNKNOWN
